levenshtein_py-1.0.3.dist-info/METADATA
levenshtein_py-1.0.3.dist-info/WHEEL
levenshtein_py.cp37-win_amd64.pyd
levenshtein_py-1.0.3.dist-info/RECORD
