Metadata-Version: 2.1
Name: levenshtein_py
Version: 1.0.3
Author: Krzysztof Zawisła <snowdropcurvemaster@gmail.com>
Author-Email: Krzysztof Zawisła <snowdropcurvemaster@gmail.com>
